dcli/__init__.py
dcli/cli.py
dcli/cmd.py
dcli/const.py
dcli/generatorCli.py
dcli/logger.py
dcli/runner.py
dcli/scoreController.py
dcli/spinCursor.py
dcli/generator/__init__.py
dcli/generator/common.py
dcli/generator/file.py
dcli/generator/languageGenerator.py
dcli/language/__init__.py
dcli/language/asset.py
dcli/language/language.py
dcli/language/c/__init__.py
dcli/language/cpp/__init__.py
dcli/language/java/__init__.py
dcli/language/java/types.json
dcli/language/kotlin/__init__.py
dcli/language/kotlin/types.json
dcli/language/python/__init__.py
dcli/model/__init__.py
dcli/model/missionUserScore.py
dcli/template/c/Dockerfile
dcli/template/c/README.md
dcli/template/c/challenge.yaml
dcli/template/c/run.sh
dcli/template/c/thumbnail.png
dcli/template/c/docs/briefing.md
dcli/template/c/docs/fr/briefing.md
dcli/template/c/src/Makefile
dcli/template/c/src/app/Logger.c
dcli/template/c/src/app/Logger.h
dcli/template/c/src/app/main.c
dcli/template/c/src/success/Target.c
dcli/template/c/src/template/Target.c
dcli/template/c/src/template/Target.h
dcli/template/cpp/Dockerfile
dcli/template/cpp/challenge.yaml
dcli/template/cpp/run.sh
dcli/template/cpp/thumbnail.png
dcli/template/cpp/docs/briefing.md
dcli/template/cpp/docs/hint1.md
dcli/template/cpp/docs/fr/briefing.md
dcli/template/cpp/docs/fr/hint1.md
dcli/template/cpp/src/Makefile
dcli/template/cpp/src/app/Logger.cpp
dcli/template/cpp/src/app/Logger.h
dcli/template/cpp/src/app/main.cpp
dcli/template/cpp/src/success/Target.cpp
dcli/template/cpp/src/template/Target.cpp
dcli/template/cpp/src/template/Target.h
dcli/template/java/Dockerfile
dcli/template/java/challenge.yaml
dcli/template/java/run.sh
dcli/template/java/template.iml
dcli/template/java/thumbnail.png
dcli/template/java/docs/briefing.md
dcli/template/java/docs/hint1.md
dcli/template/java/docs/fr/briefing.md
dcli/template/java/docs/fr/hint1.md
dcli/template/java/src/main/java/app/Logger.java
dcli/template/java/src/main/java/app/Run.java
deadlock_cli-1.2.7.dist-info/LICENSE
deadlock_cli-1.2.7.dist-info/METADATA
deadlock_cli-1.2.7.dist-info/WHEEL
deadlock_cli-1.2.7.dist-info/top_level.txt
deadlock_cli-1.2.7.dist-info/RECORD
