Metadata-Version: 2.1
Name: deadlock-cli
Version: 1.2.7
Summary: CLI tools for Deadlock challenges.
Home-page: https://github.com/deadlock-resources/dcli
Author: Slayug
Author-email: apuret@takima.fr
License: UNKNOWN
Platform: UNKNOWN
Classifier: Programming Language :: Python :: 3
Classifier: License :: OSI Approved :: MIT License
Classifier: Operating System :: OS Independent
Requires-Python: >=3.2
License-File: LICENSE
Requires-Dist: inquirer
Requires-Dist: PyInquirer
Requires-Dist: fire
Requires-Dist: Jinja2
Requires-Dist: colored
Requires-Dist: Flask
Requires-Dist: jsonify
Requires-Dist: requests
Requires-Dist: pyyaml
